{
  "adult": false,
  "backdrop_path": "/7eK8FJr4fqq3J5W2xvlr2GVaep2.jpg",
  "genre_ids": [
    14,
    18,
    10749
  ],
  "id": 8966,
  "original_language": "en",
  "original_title": "Twilight",
  "overview": "Isabella Swan, 17 ans, déménage à Forks, petite ville pluvieuse dans l'État de Washington, pour vivre avec son père. Elle s'attend à ce que sa nouvelle vie soit aussi ennuyeuse que la ville elle-même. Or, au lycée, elle est terriblement intriguée par le comportement d'une étrange fratrie, deux filles et trois garçons. Bella tombe follement amoureuse de l'un d'eux, Edward Cullen. Une relation sensuelle et dangereuse commence alors entre les deux jeunes gens : lorsque Isabella comprend que Edward est un vampire, il est déjà trop tard.",
  "popularity": 223.943,
  "poster_path": "/8phJ4i9m1tBDJbOwwQPvdeWhN2h.jpg",
  "release_date": "2008-11-20",
  "title": "Twilight, chapitre 1 : Fascination",
  "video": false,
  "vote_average": 6.291,
  "vote_count": 13231
}